ilm_limiter/__init__.py
ilm_limiter-1.0.0.dist-info/METADATA
ilm_limiter-1.0.0.dist-info/WHEEL
ilm_limiter-1.0.0.dist-info/top_level.txt
ilm_limiter-1.0.0.dist-info/RECORD
