Metadata-Version: 2.4
Name: ilm_limiter
Version: 1.0.0
Summary: Fake ilm_limiter for dependency confusion demo
Home-page: https://example.com
Author: SecurityDemo
Author-email: demo@example.com
Dynamic: author
Dynamic: author-email
Dynamic: home-page
Dynamic: summary
